option/__init__.py
option/option.py
option/py.typed
option_python-0.0.2.dist-info/LICENSE
option_python-0.0.2.dist-info/METADATA
option_python-0.0.2.dist-info/WHEEL
option_python-0.0.2.dist-info/RECORD
